[{
    "image":"https://www.planwallpaper.com/static/cache/c3/8e/c38eb072637d70294527e9ef6dbf4f04.jpg",
    "date":"16/08/2017"
},{
    "image":"https://www.planwallpaper.com/static/cache/1a/6b/1a6bea3d9461d7f684dd00f3fab773da.jpg",
    "date":"17/08/2017"
},{
    "image":"https://www.planwallpaper.com/static/cache/2f/b7/2fb761e9b418c48713ac156356a2b00f.jpg",
    "date":"17/08/2017"
},{
    "image":"http://lorempixel.com/1920/1080/nature/4",
    "date":"18/08/2017"
},{
    "image":"http://lorempixel.com/1920/1080/nature/5",
    "date":"18/08/2017"
},{
    "image":"https://www.planwallpaper.com/static/images/Happy-New-Year-11.jpg",
    "date":"19/08/2017"
},{
    "image":"https://www.planwallpaper.com/static/images/thank-you5_ailtR5e.jpg",
    "date":"19/08/2017"
},{
    "image":"https://www.planwallpaper.com/static/images/ThankYou-71.jpg",
    "date":"19/08/2017"
},{
    "image":"https://www.planwallpaper.com/static/images/Happy-New-Year-11.jpg",
    "date":"19/08/2017"
}]
